{
  "$schema": "https://developer.microsoft.com/json-schemas/fabric/item/report/definition/visualContainer/2.2.0/schema.json",
  "name": "bf885a9e7bd0878c0d8c",
  "position": {
    "x": 1296,
    "y": 216,
    "z": 14000,
    "height": 168,
    "width": 312,
    "tabOrder": 14000
  },
  "visual": {
    "visualType": "card",
    "query": {
      "queryState": {
        "Values": {
          "projections": [
            {
              "field": {
                "Measure": {
                  "Expression": {
                    "SourceRef": {
                      "Schema": "extension",
                      "Entity": "measures_"
                    }
                  },
                  "Property": "Count of Orders Available"
                }
              },
              "queryRef": "measures_.Count of Orders Available",
              "nativeQueryRef": "Available Orders ",
              "displayName": "Available Orders "
            }
          ]
        }
      },
      "sortDefinition": {
        "isDefaultSort": true
      }
    },
    "objects": {
      "labels": [
        {
          "properties": {
            "fontSize": {
              "expr": {
                "Literal": {
                  "Value": "45D"
                }
              }
            }
          }
        }
      ],
      "categoryLabels": [
        {
          "properties": {
            "fontSize": {
              "expr": {
                "Literal": {
                  "Value": "18D"
                }
              }
            }
          }
        }
      ]
    },
    "visualContainerObjects": {
      "title": [
        {
          "properties": {
            "show": {
              "expr": {
                "Literal": {
                  "Value": "true"
                }
              }
            },
            "titleWrap": {
              "expr": {
                "Literal": {
                  "Value": "true"
                }
              }
            },
            "alignment": {
              "expr": {
                "Literal": {
                  "Value": "'center'"
                }
              }
            },
            "fontSize": {
              "expr": {
                "Literal": {
                  "Value": "18D"
                }
              }
            }
          }
        }
      ],
      "background": [
        {
          "properties": {
            "show": {
              "expr": {
                "Literal": {
                  "Value": "true"
                }
              }
            },
            "color": {
              "solid": {
                "color": {
                  "expr": {
                    "Literal": {
                      "Value": "'#484545'"
                    }
                  }
                }
              }
            },
            "transparency": {
              "expr": {
                "Literal": {
                  "Value": "0D"
                }
              }
            }
          }
        }
      ],
      "lockAspect": [
        {
          "properties": {
            "show": {
              "expr": {
                "Literal": {
                  "Value": "true"
                }
              }
            }
          }
        }
      ],
      "border": [
        {
          "properties": {
            "show": {
              "expr": {
                "Literal": {
                  "Value": "true"
                }
              }
            },
            "radius": {
              "expr": {
                "Literal": {
                  "Value": "20D"
                }
              }
            },
            "width": {
              "expr": {
                "Literal": {
                  "Value": "1D"
                }
              }
            }
          }
        }
      ],
      "visualTooltip": [
        {
          "properties": {
            "show": {
              "expr": {
                "Literal": {
                  "Value": "true"
                }
              }
            },
            "type": {
              "expr": {
                "Literal": {
                  "Value": "'Canvas'"
                }
              }
            },
            "section": {
              "expr": {
                "Literal": {
                  "Value": "'ReportSection2d05c2e8221bc17ee575'"
                }
              }
            }
          }
        }
      ],
      "visualHeader": [
        {
          "properties": {
            "background": {
              "solid": {
                "color": {
                  "expr": {
                    "Literal": {
                      "Value": "'#3a3a3a'"
                    }
                  }
                }
              }
            },
            "border": {
              "solid": {
                "color": {
                  "expr": {
                    "Literal": {
                      "Value": "'#3a3a3a'"
                    }
                  }
                }
              }
            },
            "foreground": {
              "solid": {
                "color": {
                  "expr": {
                    "Literal": {
                      "Value": "'#FFFFFF'"
                    }
                  }
                }
              }
            }
          }
        }
      ],
      "padding": [
        {
          "properties": {
            "top": {
              "expr": {
                "Literal": {
                  "Value": "20D"
                }
              }
            }
          }
        }
      ]
    },
    "drillFilterOtherVisuals": true
  },
  "filterConfig": {
    "filters": [
      {
        "name": "5704ea90021c27288514",
        "field": {
          "Column": {
            "Expression": {
              "SourceRef": {
                "Entity": "Calendar"
              }
            },
            "Property": "Date"
          }
        },
        "type": "RelativeDate",
        "filter": {
          "Version": 2,
          "From": [
            {
              "Name": "c",
              "Entity": "Calendar",
              "Type": 0
            }
          ],
          "Where": [
            {
              "Condition": {
                "Comparison": {
                  "ComparisonKind": 0,
                  "Left": {
                    "Column": {
                      "Expression": {
                        "SourceRef": {
                          "Source": "c"
                        }
                      },
                      "Property": "Date"
                    }
                  },
                  "Right": {
                    "DateSpan": {
                      "Expression": {
                        "Now": {}
                      },
                      "TimeUnit": 0
                    }
                  }
                }
              }
            }
          ]
        },
        "howCreated": "User"
      },
      {
        "name": "9557c07de2db0016b82a",
        "field": {
          "Column": {
            "Expression": {
              "SourceRef": {
                "Entity": "orders"
              }
            },
            "Property": "id"
          }
        },
        "type": "Advanced",
        "filter": {
          "Version": 2,
          "From": [
            {
              "Name": "o",
              "Entity": "orders",
              "Type": 0
            }
          ],
          "Where": [
            {
              "Condition": {
                "Not": {
                  "Expression": {
                    "Contains": {
                      "Left": {
                        "Column": {
                          "Expression": {
                            "SourceRef": {
                              "Source": "o"
                            }
                          },
                          "Property": "id"
                        }
                      },
                      "Right": {
                        "Literal": {
                          "Value": "'s'"
                        }
                      }
                    }
                  }
                }
              }
            }
          ]
        },
        "howCreated": "User"
      }
    ]
  }
}