{
  "$schema": "https://developer.microsoft.com/json-schemas/fabric/item/report/definition/visualContainer/2.2.0/schema.json",
  "name": "20acecf961ac1edd7942",
  "position": {
    "x": 912,
    "y": 384,
    "z": 4000,
    "height": 320,
    "width": 352,
    "tabOrder": 4000
  },
  "visual": {
    "visualType": "tableEx",
    "query": {
      "queryState": {
        "Values": {
          "projections": [
            {
              "field": {
                "Column": {
                  "Expression": {
                    "SourceRef": {
                      "Entity": "salesperson_key"
                    }
                  },
                  "Property": "Name"
                }
              },
              "queryRef": "salesperson_key.Name",
              "nativeQueryRef": "Name"
            },
            {
              "field": {
                "Column": {
                  "Expression": {
                    "SourceRef": {
                      "Entity": "Calendar"
                    }
                  },
                  "Property": "Month / Year"
                }
              },
              "queryRef": "Calendar.Month / Year",
              "nativeQueryRef": "Month / Year"
            },
            {
              "field": {
                "Measure": {
                  "Expression": {
                    "SourceRef": {
                      "Entity": "measures_"
                    }
                  },
                  "Property": "Total Sales BWS"
                }
              },
              "queryRef": "orders.Total Sals BWS",
              "displayName": "Total BWS"
            }
          ]
        }
      },
      "sortDefinition": {
        "sort": [
          {
            "field": {
              "Column": {
                "Expression": {
                  "SourceRef": {
                    "Entity": "Calendar"
                  }
                },
                "Property": "Month / Year"
              }
            },
            "direction": "Ascending"
          }
        ]
      }
    },
    "objects": {
      "columnWidth": [
        {
          "properties": {
            "value": {
              "expr": {
                "Literal": {
                  "Value": "122.48148148148148D"
                }
              }
            }
          },
          "selector": {
            "metadata": "salesperson_key.Name"
          }
        }
      ]
    },
    "visualContainerObjects": {
      "title": [
        {
          "properties": {
            "titleWrap": {
              "expr": {
                "Literal": {
                  "Value": "true"
                }
              }
            }
          }
        }
      ],
      "background": [
        {
          "properties": {
            "show": {
              "expr": {
                "Literal": {
                  "Value": "true"
                }
              }
            },
            "color": {
              "solid": {
                "color": {
                  "expr": {
                    "Literal": {
                      "Value": "'#484545'"
                    }
                  }
                }
              }
            },
            "transparency": {
              "expr": {
                "Literal": {
                  "Value": "0D"
                }
              }
            }
          }
        }
      ],
      "border": [
        {
          "properties": {
            "show": {
              "expr": {
                "Literal": {
                  "Value": "true"
                }
              }
            },
            "radius": {
              "expr": {
                "Literal": {
                  "Value": "20D"
                }
              }
            },
            "width": {
              "expr": {
                "Literal": {
                  "Value": "1D"
                }
              }
            }
          }
        }
      ],
      "visualHeader": [
        {
          "properties": {
            "background": {
              "solid": {
                "color": {
                  "expr": {
                    "Literal": {
                      "Value": "'#3a3a3a'"
                    }
                  }
                }
              }
            },
            "border": {
              "solid": {
                "color": {
                  "expr": {
                    "Literal": {
                      "Value": "'#3a3a3a'"
                    }
                  }
                }
              }
            },
            "foreground": {
              "solid": {
                "color": {
                  "expr": {
                    "Literal": {
                      "Value": "'#FFFFFF'"
                    }
                  }
                }
              }
            }
          }
        }
      ],
      "padding": [
        {
          "properties": {
            "top": {
              "expr": {
                "Literal": {
                  "Value": "5D"
                }
              }
            }
          }
        }
      ]
    },
    "drillFilterOtherVisuals": true
  },
  "filterConfig": {
    "filters": [
      {
        "name": "90ad90a506683dcaa24d",
        "field": {
          "Measure": {
            "Expression": {
              "SourceRef": {
                "Entity": "measures_"
              }
            },
            "Property": "Total Sales BWS"
          }
        },
        "type": "Advanced",
        "filter": {
          "Version": 2,
          "From": [
            {
              "Name": "m",
              "Entity": "measures_",
              "Type": 0
            }
          ],
          "Where": [
            {
              "Condition": {
                "Not": {
                  "Expression": {
                    "Comparison": {
                      "ComparisonKind": 0,
                      "Left": {
                        "Measure": {
                          "Expression": {
                            "SourceRef": {
                              "Source": "m"
                            }
                          },
                          "Property": "Total Sales BWS"
                        }
                      },
                      "Right": {
                        "Literal": {
                          "Value": "0L"
                        }
                      }
                    }
                  }
                }
              }
            }
          ]
        }
      },
      {
        "name": "912a4660dbe84d61a2a3",
        "field": {
          "Column": {
            "Expression": {
              "SourceRef": {
                "Entity": "salesperson_key"
              }
            },
            "Property": "Name"
          }
        },
        "type": "Categorical",
        "filter": {
          "Version": 2,
          "From": [
            {
              "Name": "s",
              "Entity": "salesperson_key",
              "Type": 0
            }
          ],
          "Where": [
            {
              "Condition": {
                "Not": {
                  "Expression": {
                    "In": {
                      "Expressions": [
                        {
                          "Column": {
                            "Expression": {
                              "SourceRef": {
                                "Source": "s"
                              }
                            },
                            "Property": "Name"
                          }
                        }
                      ],
                      "Values": [
                        [
                          {
                            "Literal": {
                              "Value": "null"
                            }
                          }
                        ]
                      ]
                    }
                  }
                }
              }
            }
          ]
        },
        "objects": {
          "general": [
            {
              "properties": {
                "isInvertedSelectionMode": {
                  "expr": {
                    "Literal": {
                      "Value": "true"
                    }
                  }
                }
              }
            }
          ]
        }
      },
      {
        "name": "bd46055d699040391d57",
        "field": {
          "Measure": {
            "Expression": {
              "SourceRef": {
                "Entity": "measures_"
              }
            },
            "Property": "Current Sales"
          }
        },
        "type": "Advanced",
        "filter": {
          "Version": 2,
          "From": [
            {
              "Name": "m",
              "Entity": "measures_",
              "Type": 0
            }
          ],
          "Where": [
            {
              "Condition": {
                "Comparison": {
                  "ComparisonKind": 2,
                  "Left": {
                    "Measure": {
                      "Expression": {
                        "SourceRef": {
                          "Source": "m"
                        }
                      },
                      "Property": "Current Sales"
                    }
                  },
                  "Right": {
                    "Literal": {
                      "Value": "1L"
                    }
                  }
                }
              }
            }
          ]
        },
        "howCreated": "User"
      }
    ]
  }
}